{
  "type": "minecraft:tree",
  "config": {
    "decorators": [],
    "dirt_provider": {
      "type": "minecraft:simple_state_provider",
      "state": {
        "Name": "minecraft:dirt"
      }
    },
    "foliage_placer": {
      "type": "minecraft:fancy_foliage_placer",
      "height": 3,
      "offset": 2,
      "radius": 2
    },
    "foliage_provider": {
      "type": "minecraft:simple_state_provider",
      "state": {
        "Name": "nomansland:walnut_leaves",
        "Properties": {
          "distance": "7",
          "persistent": "false",
          "waterlogged": "false"
        }
      }
    },
    "force_dirt": false,
    "ignore_vines": true,
    "minimum_size": {
      "type": "minecraft:two_layers_feature_size",
      "limit": 0,
      "lower_size": 0,
      "min_clipped_height": 6,
      "upper_size": 0
    },
    "trunk_placer": {
      "type": "nomansland:branchy_trunk_placer",
      "base_height": 5,
      "height_rand_a": 4,
      "height_rand_b": 0,
      "branch_length": 2,
      "branch_count": 2,
      "branch_min_height": 4,
      "branch_max_height": 3
    },
    "trunk_provider": {
      "type": "minecraft:simple_state_provider",
      "state": {
        "Name": "nomansland:walnut_log",
        "Properties": {
          "axis": "y"
        }
      }
    }
  }
}