{
  "required": true,
  "package": "com.farcr.nomansland.common.mixin",
  "compatibilityLevel": "JAVA_21",
  "refmap": "nomansland.refmap.json",
  "mixins": [
    "AbstractCauldronBlockMixin",
    "BaseSpawnerMixin",
    "BiomeMixin",
    "BlockEntityAccessor",
    "EntityMixin",
    "EntityTypeMixin",
    "LivingEntityMixin",
    "MobMixin",
    "ServerLevelMixin",
    "SnowAndFreezeFeatureMixin",
    "SpreadingSnowyDirtBlockMixin",
    "ProjectileMixin",
    "ThrownPotionMixin",
    "variants.AbstractFishMixin",
    "variants.CodMixin",
    "variants.CowMixin",
    "variants.DolphinMixin",
    "variants.FoxMixin",
    "variants.FrogMixin",
    "variants.GoatMixin",
    "variants.MushroomCowMixin",
    "variants.PigMixin",
    "variants.SalmonMixin",
    "variants.SheepMixin",
    "variants.TurtleMixin"
  ],
  "client": [
    "ModelBlockRendererMixin",
    "RenderLayerMixin",
    "variants.CodRendererMixin",
    "variants.CowModelMixin",
    "variants.CowRendererMixin",
    "variants.DolphinRendererMixin",
    "variants.FoxRendererMixin",
    "variants.GoatRendererMixin",
    "variants.MushroomCowMushroomLayerMixin",
    "variants.MushroomCowRendererMixin",
    "variants.PigModelMixin",
    "variants.PigRendererMixin",
    "variants.QuadrupedModelMixin",
    "variants.SaddleLayerMixin",
    "variants.SalmonRendererMixin",
    "variants.SheepModelMixin",
    "variants.SheepRendererMixin",
    "variants.TurtleRendererMixin"
  ],
  "injectors": {
    "defaultRequire": 1
  },
  "minVersion": "0.8"
}